immut/__init__.py
immut/container.py
immut/tests/__init__.py
immut/tests/test_container.py
immut-0.2.0.dist-info/DESCRIPTION.rst
immut-0.2.0.dist-info/METADATA
immut-0.2.0.dist-info/metadata.json
immut-0.2.0.dist-info/RECORD
immut-0.2.0.dist-info/top_level.txt
immut-0.2.0.dist-info/WHEEL
