Metadata-Version: 2.0
Name: immut
Version: 0.2.0
Summary: An immutable container library for python
Home-page: https://github.com/jcomo/immut
Author: Jonathan Como
Author-email: jonathan.como@gmail.com
License: UNKNOWN
Keywords: development immutable container functional
Platform: UNKNOWN
Classifier: Programming Language :: Python :: 2
Classifier: Programming Language :: Python :: 2.6
Classifier: Programming Language :: Python :: 2.7
